convertable/yamltojson.py
convertable-0.1.0.dist-info/METADATA
convertable-0.1.0.dist-info/WHEEL
convertable-0.1.0.dist-info/entry_points.txt
convertable-0.1.0.dist-info/RECORD
